dl85Optimizer.cp39-win_amd64.pyd
pydl85/__init__.py
pydl85/_version.py
pydl85/errors/__init__.py
pydl85/errors/errors.py
pydl85/predictors/__init__.py
pydl85/predictors/predictor.py
pydl85/predictors/predictor_backup.py
pydl85/predictors/predictor_backup2.py
pydl85/predictors/predictor_backup3.py
pydl85/supervised/__init__.py
pydl85/supervised/classifiers/__init__.py
pydl85/supervised/classifiers/boosting.py
pydl85/supervised/classifiers/classifier.py
pydl85/unsupervised/__init__.py
pydl85/unsupervised/clustering.py
pydl8.5-0.1.8.dist-info/LICENSE.txt
pydl8.5-0.1.8.dist-info/METADATA
pydl8.5-0.1.8.dist-info/WHEEL
pydl8.5-0.1.8.dist-info/top_level.txt
pydl8.5-0.1.8.dist-info/zip-safe
pydl8.5-0.1.8.dist-info/RECORD
